{
  "mixin_path": "app/core/session/voice_mixin.py",
  "class_name": "VoiceMixin",
  "docstring": "Voice I/O mixin.\n\nExtracted from :mod:`app.core.session.session_controller`. Owns the\nclient-side audio I/O surface (mic source, frame feed, listeners),\nVAD/STT settings, the TTS provider/voice surface + runtime prewarm,\nand the STT-partial / backchannel / mood-state listener wiring. State\nownership stays on ``SessionController.__init__``.\n\nNB: tests that patched ``app.core.session.session_controller.<symbol>``\nfor any moved method must patch\n``app.core.session.voice_mixin.<symbol>`` instead.",
  "class_doc": "Audio I/O + VAD/STT settings + TTS/prewarm + STT partials/backchannel.",
  "methods": [
    "mic_source",
    "feed_audio_start",
    "feed_audio_frame",
    "feed_audio_end",
    "set_audio_frame_listener",
    "_emit_audio_frame",
    "_emit_audio_frame_end",
    "barge_in_enabled",
    "set_barge_in_enabled",
    "vad_level_threshold",
    "set_vad_level_threshold",
    "vad_silence_seconds",
    "set_vad_silence_seconds",
    "stt_model",
    "set_stt_model",
    "tts_provider",
    "list_tts_providers",
    "tts_voice",
    "list_tts_voices",
    "set_tts_voice",
    "get_tts_model_status",
    "stop_tts",
    "is_tts_playing",
    "speak_text",
    "set_tts_provider",
    "prewarm_tts",
    "prewarm_runtime",
    "_prewarm_local_worker_model",
    "_prewarm_embedder",
    "add_mood_state_listener",
    "add_stt_partial_listener",
    "add_backchannel_listener",
    "feed_stt_partial",
    "reset_backchannel_state",
    "_notify_mood_state"
  ],
  "extra_imports": [],
  "omit_auto": ["log"],
  "stub": "# Voice I/O + VAD/STT + TTS/prewarm + STT-partial/backchannel methods\n    # live in voice_mixin.py."
}
